setup.py
django_monit.egg-info/PKG-INFO
django_monit.egg-info/SOURCES.txt
django_monit.egg-info/dependency_links.txt
django_monit.egg-info/requires.txt
django_monit.egg-info/top_level.txt
monit/__init__.py
monit/models.py
monit/tests.py
monit/urls.py
monit/views.py