Metadata-Version: 1.0
Name: django-monit
Version: 0.1a
Summary: A simple Django-based Monit collector
Home-page: http://github.com/johnpaulett/django-monit
Author: John Paulett
Author-email: john@paulett.org
License: BSD
Keywords: monit monitoring django
Platform: UNKNOWN
